oracula/__init__.py
oracula/version.py
oracula/core/__init__.py
oracula-0.0.2.dist-info/LICENSE
oracula-0.0.2.dist-info/METADATA
oracula-0.0.2.dist-info/WHEEL
oracula-0.0.2.dist-info/top_level.txt
oracula-0.0.2.dist-info/RECORD
