Metadata-Version: 2.1
Name: oracula
Version: 0.0.2
Summary: Adaptive experimentation with the help of adaptive computations
Author-email: Alexander Fedotov <alex.fedotov@aol.com>
Project-URL: Homepage, https://github.com/alxfed/oracula
Project-URL: Bug Tracker, https://github.com/alxfed/oracula/issues
Classifier: Programming Language :: Python :: 3
Classifier: License :: OSI Approved :: MIT License
Classifier: Operating System :: OS Independent
Requires-Python: >=3.9
License-File: LICENSE
